LICENSE.txt
MANIFEST.in
README.md
setup.py
PPLG/__init__.py
PPLG/__main__.py
PPLG/m1.txt
PPLG/m2.txt
PPLG/lib/Generate.py
PPLG/lib/Generate_cy.c
PPLG/lib/Generate_cy.pyx
PPLG/lib/__init__.py
PyPassListGen.egg-info/PKG-INFO
PyPassListGen.egg-info/SOURCES.txt
PyPassListGen.egg-info/dependency_links.txt
PyPassListGen.egg-info/entry_points.txt
PyPassListGen.egg-info/requires.txt
PyPassListGen.egg-info/top_level.txt