Metadata-Version: 2.1
Name: PyPassListGen
Version: 1.0.1
Summary: PyPassListGen is a python script that allows you to generate password lists fast and easily.
Home-page: https://github.com/MPCodeWriter21/PyPassListGen
Author: CodeWriter21(Mehrad Pooryoussof)
Author-email: <CodeWriter21@gmail.com>
License:                                  Apache License
Keywords: python,pass,password,passlist,passwordlist,password-list,password list generator,PyPassListGen,CodeWriter21
Platform: UNKNOWN
Classifier: Intended Audience :: Developers
Classifier: Programming Language :: Python :: 3
License-File: LICENSE.txt
